{
  "legislative_session": "89R",
  "identifier": "HJR 145",
  "title": "Proposing a constitutional amendment exempting tangible personal property from ad valorem taxation.",
  "from_organization": "~{\"classification\": \"lower\"}",
  "classification": [
    "joint resolution"
  ],
  "subject": [
    "Property Interests--Personal Property (I0600)",
    "Property Interests--Real Property (I0595)",
    "Resolutions--Constitutional Amendments (I0661)",
    "Taxation--Property-Appraisals & Appraisal Districts (I0792)",
    "Taxation--Property-Assessment & Collection (I0798)",
    "Taxation--Property-Exemptions (I0793)",
    "Transportation--Railroads (I0821)"
  ],
  "abstracts": [],
  "other_titles": [],
  "other_identifiers": [
    {
      "identifier": "ocd-bill-tx-89r-hjr145"
    }
  ],
  "actions": [
    {
      "description": "Filed",
      "date": "2025-02-20",
      "organization_id": "~{\"classification\": \"lower\"}",
      "classification": [
        "filing"
      ],
      "related_entities": [],
      "_processing": {
        "log_file_created": "2026-06-27T13:39:14Z"
      }
    },
    {
      "description": "Read first time",
      "date": "2025-03-19",
      "organization_id": "~{\"classification\": \"lower\"}",
      "classification": [
        "introduction",
        "reading-1"
      ],
      "related_entities": [],
      "_processing": {
        "log_file_created": "2026-06-27T13:39:14Z"
      }
    },
    {
      "description": "Referred to Ways & Means",
      "date": "2025-03-19",
      "organization_id": "~{\"classification\": \"lower\"}",
      "classification": [
        "referral-committee"
      ],
      "related_entities": [
        {
          "name": "Ways & Means",
          "entity_type": "organization",
          "organization_id": null
        }
      ],
      "_processing": {
        "log_file_created": "2026-06-27T13:39:14Z"
      }
    }
  ],
  "sponsorships": [
    {
      "name": "Metcalf",
      "classification": "primary",
      "entity_type": "person",
      "primary": true,
      "person_id": "~{\"name\": \"Metcalf\"}",
      "organization_id": null
    }
  ],
  "related_bills": [],
  "versions": [
    {
      "note": "Introduced",
      "links": [
        {
          "url": "http://capitol.texas.gov/tlodocs/89R/billtext/html/HJ00145I.HTM",
          "media_type": "text/html"
        },
        {
          "url": "http://capitol.texas.gov/tlodocs/89R/billtext/pdf/HJ00145I.PDF",
          "media_type": "application/pdf"
        }
      ],
      "date": "",
      "classification": ""
    }
  ],
  "documents": [],
  "citations": [],
  "sources": [
    {
      "url": "ftp://ftp.legis.state.tx.us/bills/89R/billhistory/house_joint_resolutions/HJR00100_HJR00199/HJR 145.xml",
      "note": ""
    },
    {
      "url": "https://capitol.texas.gov/BillLookup/History.aspx?LegSess=89R&Bill=HJR145",
      "note": ""
    }
  ],
  "extras": {},
  "jurisdiction": {
    "id": "ocd-jurisdiction/country:us/state:tx/government",
    "name": "Texas",
    "classification": "state",
    "division_id": "ocd-division/country:us/state:tx"
  },
  "_processing": {
    "logs_latest_update": "2026-06-27T13:39:14Z"
  }
}