{
  "legislative_session": "89R",
  "identifier": "HB 476",
  "title": "Relating to the maximum permitted rate of interest, sum of fees, and other amounts that may be charged in connection with deferred presentment transactions; creating a criminal offense.",
  "from_organization": "~{\"classification\": \"lower\"}",
  "classification": [
    "bill"
  ],
  "subject": [
    "Consumer Protection (I0080)",
    "DEFERRED PRESENTMENT TRANSACTIONS (S0380)",
    "Financial--General (I0365)"
  ],
  "abstracts": [],
  "other_titles": [],
  "other_identifiers": [
    {
      "identifier": "ocd-bill-tx-89r-hb476"
    }
  ],
  "actions": [
    {
      "description": "Filed",
      "date": "2024-11-12",
      "organization_id": "~{\"classification\": \"lower\"}",
      "classification": [
        "filing"
      ],
      "related_entities": [],
      "_processing": {
        "log_file_created": "2026-06-27T13:39:20Z"
      }
    },
    {
      "description": "Read first time",
      "date": "2025-02-28",
      "organization_id": "~{\"classification\": \"lower\"}",
      "classification": [
        "introduction",
        "reading-1"
      ],
      "related_entities": [],
      "_processing": {
        "log_file_created": "2026-06-27T13:39:20Z"
      }
    },
    {
      "description": "Referred to Pensions, Investments & Financial Services",
      "date": "2025-02-28",
      "organization_id": "~{\"classification\": \"lower\"}",
      "classification": [
        "referral-committee"
      ],
      "related_entities": [
        {
          "name": "Pensions, Investments & Financial Services",
          "entity_type": "organization",
          "organization_id": null
        }
      ],
      "_processing": {
        "log_file_created": "2026-06-27T13:39:20Z"
      }
    }
  ],
  "sponsorships": [
    {
      "name": "Bucy",
      "classification": "primary",
      "entity_type": "person",
      "primary": true,
      "person_id": "~{\"name\": \"Bucy\"}",
      "organization_id": null
    }
  ],
  "related_bills": [],
  "versions": [
    {
      "note": "Introduced",
      "links": [
        {
          "url": "http://capitol.texas.gov/tlodocs/89R/billtext/html/HB00476I.HTM",
          "media_type": "text/html"
        },
        {
          "url": "http://capitol.texas.gov/tlodocs/89R/billtext/pdf/HB00476I.PDF",
          "media_type": "application/pdf"
        }
      ],
      "date": "",
      "classification": ""
    }
  ],
  "documents": [],
  "citations": [],
  "sources": [
    {
      "url": "ftp://ftp.legis.state.tx.us/bills/89R/billhistory/house_bills/HB00400_HB00499/HB 476.xml",
      "note": ""
    },
    {
      "url": "https://capitol.texas.gov/BillLookup/History.aspx?LegSess=89R&Bill=HB476",
      "note": ""
    }
  ],
  "extras": {},
  "jurisdiction": {
    "id": "ocd-jurisdiction/country:us/state:tx/government",
    "name": "Texas",
    "classification": "state",
    "division_id": "ocd-division/country:us/state:tx"
  },
  "_processing": {
    "logs_latest_update": "2026-06-27T13:39:20Z"
  }
}