{
  "action": {
    "description": "Testimony taken/registration(s) recorded in subcommittee",
    "occurred_at": "2025-05-05",
    "jurisdiction_id": "~{\"classification\": \"lower\"}",
    "session_id": "89R",
    "entity_type": "bill",
    "classifications": [],
    "related_entities": [],
    "sources": [
      {
        "url": "ftp://ftp.legis.state.tx.us/bills/89R/billhistory/senate_bills/SB01900_SB01999/SB 1931.xml",
        "note": ""
      },
      {
        "url": "https://capitol.texas.gov/BillLookup/History.aspx?LegSess=89R&Bill=SB1931",
        "note": ""
      }
    ]
  },
  "bill_id": "SB 1931"
}