{
  "legislative_session": "89R",
  "identifier": "HB 1789",
  "title": "Relating to enhancing the criminal penalty for the offense of intoxication manslaughter in certain circumstances.",
  "from_organization": "~{\"classification\": \"lower\"}",
  "classification": [
    "bill"
  ],
  "subject": [
    "Criminal Procedure--Sentencing & Punishment (I0205)",
    "Vehicles & Traffic--DWI & DUID (I0863)"
  ],
  "abstracts": [],
  "other_titles": [],
  "other_identifiers": [
    {
      "identifier": "ocd-bill-tx-89r-hb1789"
    }
  ],
  "actions": [
    {
      "description": "Filed",
      "date": "2025-01-08",
      "organization_id": "~{\"classification\": \"lower\"}",
      "classification": [
        "filing"
      ],
      "related_entities": [],
      "_processing": {
        "log_file_created": "2026-06-27T13:39:04Z"
      }
    },
    {
      "description": "Read first time",
      "date": "2025-03-14",
      "organization_id": "~{\"classification\": \"lower\"}",
      "classification": [
        "introduction",
        "reading-1"
      ],
      "related_entities": [],
      "_processing": {
        "log_file_created": "2026-06-27T13:39:04Z"
      }
    },
    {
      "description": "Referred to Criminal Jurisprudence",
      "date": "2025-03-14",
      "organization_id": "~{\"classification\": \"lower\"}",
      "classification": [
        "referral-committee"
      ],
      "related_entities": [
        {
          "name": "Criminal Jurisprudence",
          "entity_type": "organization",
          "organization_id": null
        }
      ],
      "_processing": {
        "log_file_created": "2026-06-27T13:39:04Z"
      }
    },
    {
      "description": "Referred directly to subcommittee by chair",
      "date": "2025-03-25",
      "organization_id": "~{\"classification\": \"lower\"}",
      "classification": [],
      "related_entities": [],
      "_processing": {
        "log_file_created": "2026-06-27T13:39:04Z"
      }
    },
    {
      "description": "Scheduled for public hearing in s/c on . . .",
      "date": "2025-04-03",
      "organization_id": "~{\"classification\": \"lower\"}",
      "classification": [],
      "related_entities": [],
      "_processing": {
        "log_file_created": "2026-06-27T13:39:04Z"
      }
    },
    {
      "description": "Considered by s/c in public hearing",
      "date": "2025-04-03",
      "organization_id": "~{\"classification\": \"lower\"}",
      "classification": [],
      "related_entities": [],
      "_processing": {
        "log_file_created": "2026-06-27T13:39:04Z"
      }
    },
    {
      "description": "Testimony taken/registration(s) recorded in subcommittee",
      "date": "2025-04-03",
      "organization_id": "~{\"classification\": \"lower\"}",
      "classification": [],
      "related_entities": [],
      "_processing": {
        "log_file_created": "2026-06-27T13:39:04Z"
      }
    },
    {
      "description": "Left pending in subcommittee",
      "date": "2025-04-03",
      "organization_id": "~{\"classification\": \"lower\"}",
      "classification": [],
      "related_entities": [],
      "_processing": {
        "log_file_created": "2026-06-27T13:39:04Z"
      }
    }
  ],
  "sponsorships": [
    {
      "name": "Gerdes",
      "classification": "primary",
      "entity_type": "person",
      "primary": true,
      "person_id": "~{\"name\": \"Gerdes\"}",
      "organization_id": null
    }
  ],
  "related_bills": [],
  "versions": [
    {
      "note": "Introduced",
      "links": [
        {
          "url": "http://capitol.texas.gov/tlodocs/89R/billtext/html/HB01789I.HTM",
          "media_type": "text/html"
        },
        {
          "url": "http://capitol.texas.gov/tlodocs/89R/billtext/pdf/HB01789I.PDF",
          "media_type": "application/pdf"
        }
      ],
      "date": "",
      "classification": ""
    }
  ],
  "documents": [
    {
      "note": "Fiscal Note (Introduced)",
      "links": [
        {
          "url": "http://capitol.texas.gov/tlodocs/89R/fiscalNotes/html/HB01789I.HTM",
          "media_type": "text/html"
        }
      ],
      "date": "",
      "classification": ""
    }
  ],
  "citations": [],
  "sources": [
    {
      "url": "ftp://ftp.legis.state.tx.us/bills/89R/billhistory/house_bills/HB01700_HB01799/HB 1789.xml",
      "note": ""
    },
    {
      "url": "https://capitol.texas.gov/BillLookup/History.aspx?LegSess=89R&Bill=HB1789",
      "note": ""
    }
  ],
  "extras": {},
  "jurisdiction": {
    "id": "ocd-jurisdiction/country:us/state:tx/government",
    "name": "Texas",
    "classification": "state",
    "division_id": "ocd-division/country:us/state:tx"
  },
  "_processing": {
    "logs_latest_update": "2026-06-27T13:39:04Z"
  }
}